stale_data_detection/__init__.py
stale_data_detection/extract_table_names.py
stale_data_detection/flag_stale_table.py
stale_data_detection/get_table_update_status.py
stale_data_detection-0.5.dist-info/.ipynb_checkpoints/PKG-INFO-checkpoint
stale_data_detection-0.5.dist-info/.ipynb_checkpoints/SOURCES-checkpoint.txt
stale_data_detection-0.5.dist-info/.ipynb_checkpoints/dependency_links-checkpoint.txt
stale_data_detection-0.5.dist-info/.ipynb_checkpoints/requires-checkpoint.txt
stale_data_detection-0.5.dist-info/.ipynb_checkpoints/top_level-checkpoint.txt
test/__init__.py
test/test_extract_tables.py
test/test_flag_stale_table.py
stale_data_detection-0.5.dist-info/LICENSE
stale_data_detection-0.5.dist-info/METADATA
stale_data_detection-0.5.dist-info/WHEEL
stale_data_detection-0.5.dist-info/top_level.txt
stale_data_detection-0.5.dist-info/RECORD
